{
  "15179017276116938414": {
    "build": {
      "command": "next build",
      "options": {
        "cwd": "apps/frontend/seller-ui",
        "tty": false
      },
      "dependsOn": [
        "^build"
      ],
      "cache": true,
      "inputs": [
        "default",
        "^production",
        {
          "externalDependencies": [
            "next"
          ]
        }
      ],
      "outputs": [
        "{workspaceRoot}/apps/frontend/seller-ui/.next/!(cache)/**/*",
        "{workspaceRoot}/apps/frontend/seller-ui/.next/!(cache)"
      ]
    },
    "dev": {
      "continuous": true,
      "command": "next dev",
      "options": {
        "cwd": "apps/frontend/seller-ui"
      }
    },
    "start": {
      "continuous": true,
      "command": "next start",
      "options": {
        "cwd": "apps/frontend/seller-ui"
      },
      "dependsOn": [
        "build"
      ]
    },
    "serve-static": {
      "continuous": true,
      "command": "next start",
      "options": {
        "cwd": "apps/frontend/seller-ui"
      },
      "dependsOn": [
        "build"
      ]
    },
    "build-deps": {
      "dependsOn": [
        "^build"
      ]
    },
    "watch-deps": {
      "continuous": true,
      "dependsOn": [
        "build-deps"
      ],
      "command": "npx nx watch --projects seller-ui --includeDependentProjects -- npx nx build-deps seller-ui"
    }
  },
  "10566484756698208366": {
    "build": {
      "command": "next build",
      "options": {
        "cwd": "apps/frontend/user-ui",
        "tty": false
      },
      "dependsOn": [
        "^build"
      ],
      "cache": true,
      "inputs": [
        "default",
        "^production",
        {
          "externalDependencies": [
            "next"
          ]
        }
      ],
      "outputs": [
        "{workspaceRoot}/apps/frontend/user-ui/.next/!(cache)/**/*",
        "{workspaceRoot}/apps/frontend/user-ui/.next/!(cache)"
      ]
    },
    "dev": {
      "continuous": true,
      "command": "next dev",
      "options": {
        "cwd": "apps/frontend/user-ui"
      }
    },
    "start": {
      "continuous": true,
      "command": "next start",
      "options": {
        "cwd": "apps/frontend/user-ui"
      },
      "dependsOn": [
        "build"
      ]
    },
    "serve-static": {
      "continuous": true,
      "command": "next start",
      "options": {
        "cwd": "apps/frontend/user-ui"
      },
      "dependsOn": [
        "build"
      ]
    },
    "build-deps": {
      "dependsOn": [
        "^build"
      ]
    },
    "watch-deps": {
      "continuous": true,
      "dependsOn": [
        "build-deps"
      ],
      "command": "npx nx watch --projects user-ui --includeDependentProjects -- npx nx build-deps user-ui"
    }
  },
  "3948072708770188524": {
    "build": {
      "command": "next build",
      "options": {
        "cwd": "apps/frontend/seller-ui",
        "tty": false
      },
      "dependsOn": [
        "^build"
      ],
      "cache": true,
      "inputs": [
        "default",
        "^production",
        {
          "externalDependencies": [
            "next"
          ]
        }
      ],
      "outputs": [
        "{workspaceRoot}/apps/frontend/seller-ui/.next/!(cache)/**/*",
        "{workspaceRoot}/apps/frontend/seller-ui/.next/!(cache)"
      ]
    },
    "dev": {
      "continuous": true,
      "command": "next dev",
      "options": {
        "cwd": "apps/frontend/seller-ui"
      }
    },
    "start": {
      "continuous": true,
      "command": "next start",
      "options": {
        "cwd": "apps/frontend/seller-ui"
      },
      "dependsOn": [
        "build"
      ]
    },
    "serve-static": {
      "continuous": true,
      "command": "next start",
      "options": {
        "cwd": "apps/frontend/seller-ui"
      },
      "dependsOn": [
        "build"
      ]
    },
    "build-deps": {
      "dependsOn": [
        "^build"
      ]
    },
    "watch-deps": {
      "continuous": true,
      "dependsOn": [
        "build-deps"
      ],
      "command": "npx nx watch --projects seller-ui --includeDependentProjects -- npx nx build-deps seller-ui"
    }
  },
  "13698433675789494350": {
    "build": {
      "command": "next build",
      "options": {
        "cwd": "apps/frontend/user-ui",
        "tty": false
      },
      "dependsOn": [
        "^build"
      ],
      "cache": true,
      "inputs": [
        "default",
        "^production",
        {
          "externalDependencies": [
            "next"
          ]
        }
      ],
      "outputs": [
        "{workspaceRoot}/apps/frontend/user-ui/.next/!(cache)/**/*",
        "{workspaceRoot}/apps/frontend/user-ui/.next/!(cache)"
      ]
    },
    "dev": {
      "continuous": true,
      "command": "next dev",
      "options": {
        "cwd": "apps/frontend/user-ui"
      }
    },
    "start": {
      "continuous": true,
      "command": "next start",
      "options": {
        "cwd": "apps/frontend/user-ui"
      },
      "dependsOn": [
        "build"
      ]
    },
    "serve-static": {
      "continuous": true,
      "command": "next start",
      "options": {
        "cwd": "apps/frontend/user-ui"
      },
      "dependsOn": [
        "build"
      ]
    },
    "build-deps": {
      "dependsOn": [
        "^build"
      ]
    },
    "watch-deps": {
      "continuous": true,
      "dependsOn": [
        "build-deps"
      ],
      "command": "npx nx watch --projects user-ui --includeDependentProjects -- npx nx build-deps user-ui"
    }
  },
  "3413583688696582055": {
    "build": {
      "command": "next build",
      "options": {
        "cwd": "apps/frontend/seller-ui",
        "tty": false
      },
      "dependsOn": [
        "^build"
      ],
      "cache": true,
      "inputs": [
        "default",
        "^production",
        {
          "externalDependencies": [
            "next"
          ]
        }
      ],
      "outputs": [
        "{workspaceRoot}/apps/frontend/seller-ui/.next/!(cache)/**/*",
        "{workspaceRoot}/apps/frontend/seller-ui/.next/!(cache)"
      ]
    },
    "dev": {
      "continuous": true,
      "command": "next dev",
      "options": {
        "cwd": "apps/frontend/seller-ui"
      }
    },
    "start": {
      "continuous": true,
      "command": "next start",
      "options": {
        "cwd": "apps/frontend/seller-ui"
      },
      "dependsOn": [
        "build"
      ]
    },
    "serve-static": {
      "continuous": true,
      "command": "next start",
      "options": {
        "cwd": "apps/frontend/seller-ui"
      },
      "dependsOn": [
        "build"
      ]
    },
    "build-deps": {
      "dependsOn": [
        "^build"
      ]
    },
    "watch-deps": {
      "continuous": true,
      "dependsOn": [
        "build-deps"
      ],
      "command": "npx nx watch --projects seller-ui --includeDependentProjects -- npx nx build-deps seller-ui"
    }
  },
  "12951641029883847493": {
    "build": {
      "command": "next build",
      "options": {
        "cwd": "apps/frontend/user-ui",
        "tty": false
      },
      "dependsOn": [
        "^build"
      ],
      "cache": true,
      "inputs": [
        "default",
        "^production",
        {
          "externalDependencies": [
            "next"
          ]
        }
      ],
      "outputs": [
        "{workspaceRoot}/apps/frontend/user-ui/.next/!(cache)/**/*",
        "{workspaceRoot}/apps/frontend/user-ui/.next/!(cache)"
      ]
    },
    "dev": {
      "continuous": true,
      "command": "next dev",
      "options": {
        "cwd": "apps/frontend/user-ui"
      }
    },
    "start": {
      "continuous": true,
      "command": "next start",
      "options": {
        "cwd": "apps/frontend/user-ui"
      },
      "dependsOn": [
        "build"
      ]
    },
    "serve-static": {
      "continuous": true,
      "command": "next start",
      "options": {
        "cwd": "apps/frontend/user-ui"
      },
      "dependsOn": [
        "build"
      ]
    },
    "build-deps": {
      "dependsOn": [
        "^build"
      ]
    },
    "watch-deps": {
      "continuous": true,
      "dependsOn": [
        "build-deps"
      ],
      "command": "npx nx watch --projects user-ui --includeDependentProjects -- npx nx build-deps user-ui"
    }
  },
  "6706170198226427237": {
    "build": {
      "command": "next build",
      "options": {
        "cwd": "apps/frontend/seller-ui",
        "tty": false
      },
      "dependsOn": [
        "^build"
      ],
      "cache": true,
      "inputs": [
        "default",
        "^production",
        {
          "externalDependencies": [
            "next"
          ]
        }
      ],
      "outputs": [
        "{workspaceRoot}/apps/frontend/seller-ui/.next/!(cache)/**/*",
        "{workspaceRoot}/apps/frontend/seller-ui/.next/!(cache)"
      ]
    },
    "dev": {
      "continuous": true,
      "command": "next dev",
      "options": {
        "cwd": "apps/frontend/seller-ui"
      }
    },
    "start": {
      "continuous": true,
      "command": "next start",
      "options": {
        "cwd": "apps/frontend/seller-ui"
      },
      "dependsOn": [
        "build"
      ]
    },
    "serve-static": {
      "continuous": true,
      "command": "next start",
      "options": {
        "cwd": "apps/frontend/seller-ui"
      },
      "dependsOn": [
        "build"
      ]
    },
    "build-deps": {
      "dependsOn": [
        "^build"
      ]
    },
    "watch-deps": {
      "continuous": true,
      "dependsOn": [
        "build-deps"
      ],
      "command": "npx nx watch --projects seller-ui --includeDependentProjects -- npx nx build-deps seller-ui"
    }
  },
  "9877734009935549924": {
    "build": {
      "command": "next build",
      "options": {
        "cwd": "apps/frontend/user-ui",
        "tty": false
      },
      "dependsOn": [
        "^build"
      ],
      "cache": true,
      "inputs": [
        "default",
        "^production",
        {
          "externalDependencies": [
            "next"
          ]
        }
      ],
      "outputs": [
        "{workspaceRoot}/apps/frontend/user-ui/.next/!(cache)/**/*",
        "{workspaceRoot}/apps/frontend/user-ui/.next/!(cache)"
      ]
    },
    "dev": {
      "continuous": true,
      "command": "next dev",
      "options": {
        "cwd": "apps/frontend/user-ui"
      }
    },
    "start": {
      "continuous": true,
      "command": "next start",
      "options": {
        "cwd": "apps/frontend/user-ui"
      },
      "dependsOn": [
        "build"
      ]
    },
    "serve-static": {
      "continuous": true,
      "command": "next start",
      "options": {
        "cwd": "apps/frontend/user-ui"
      },
      "dependsOn": [
        "build"
      ]
    },
    "build-deps": {
      "dependsOn": [
        "^build"
      ]
    },
    "watch-deps": {
      "continuous": true,
      "dependsOn": [
        "build-deps"
      ],
      "command": "npx nx watch --projects user-ui --includeDependentProjects -- npx nx build-deps user-ui"
    }
  },
  "13475421381638547532": {
    "build": {
      "command": "next build",
      "options": {
        "cwd": "apps/frontend/seller-ui",
        "tty": false
      },
      "dependsOn": [
        "^build"
      ],
      "cache": true,
      "inputs": [
        "default",
        "^production",
        {
          "externalDependencies": [
            "next"
          ]
        }
      ],
      "outputs": [
        "{workspaceRoot}/apps/frontend/seller-ui/.next/!(cache)/**/*",
        "{workspaceRoot}/apps/frontend/seller-ui/.next/!(cache)"
      ]
    },
    "dev": {
      "continuous": true,
      "command": "next dev",
      "options": {
        "cwd": "apps/frontend/seller-ui"
      }
    },
    "start": {
      "continuous": true,
      "command": "next start",
      "options": {
        "cwd": "apps/frontend/seller-ui"
      },
      "dependsOn": [
        "build"
      ]
    },
    "serve-static": {
      "continuous": true,
      "command": "next start",
      "options": {
        "cwd": "apps/frontend/seller-ui"
      },
      "dependsOn": [
        "build"
      ]
    },
    "build-deps": {
      "dependsOn": [
        "^build"
      ]
    },
    "watch-deps": {
      "continuous": true,
      "dependsOn": [
        "build-deps"
      ],
      "command": "npx nx watch --projects seller-ui --includeDependentProjects -- npx nx build-deps seller-ui"
    }
  },
  "6795702260613676861": {
    "build": {
      "command": "next build",
      "options": {
        "cwd": "apps/frontend/user-ui",
        "tty": false
      },
      "dependsOn": [
        "^build"
      ],
      "cache": true,
      "inputs": [
        "default",
        "^production",
        {
          "externalDependencies": [
            "next"
          ]
        }
      ],
      "outputs": [
        "{workspaceRoot}/apps/frontend/user-ui/.next/!(cache)/**/*",
        "{workspaceRoot}/apps/frontend/user-ui/.next/!(cache)"
      ]
    },
    "dev": {
      "continuous": true,
      "command": "next dev",
      "options": {
        "cwd": "apps/frontend/user-ui"
      }
    },
    "start": {
      "continuous": true,
      "command": "next start",
      "options": {
        "cwd": "apps/frontend/user-ui"
      },
      "dependsOn": [
        "build"
      ]
    },
    "serve-static": {
      "continuous": true,
      "command": "next start",
      "options": {
        "cwd": "apps/frontend/user-ui"
      },
      "dependsOn": [
        "build"
      ]
    },
    "build-deps": {
      "dependsOn": [
        "^build"
      ]
    },
    "watch-deps": {
      "continuous": true,
      "dependsOn": [
        "build-deps"
      ],
      "command": "npx nx watch --projects user-ui --includeDependentProjects -- npx nx build-deps user-ui"
    }
  },
  "14710183436673657368": {
    "build": {
      "command": "next build",
      "options": {
        "cwd": "apps/frontend/seller-ui",
        "tty": false
      },
      "dependsOn": [
        "^build"
      ],
      "cache": true,
      "inputs": [
        "default",
        "^production",
        {
          "externalDependencies": [
            "next"
          ]
        }
      ],
      "outputs": [
        "{workspaceRoot}/apps/frontend/seller-ui/.next/!(cache)/**/*",
        "{workspaceRoot}/apps/frontend/seller-ui/.next/!(cache)"
      ]
    },
    "dev": {
      "continuous": true,
      "command": "next dev",
      "options": {
        "cwd": "apps/frontend/seller-ui"
      }
    },
    "start": {
      "continuous": true,
      "command": "next start",
      "options": {
        "cwd": "apps/frontend/seller-ui"
      },
      "dependsOn": [
        "build"
      ]
    },
    "serve-static": {
      "continuous": true,
      "command": "next start",
      "options": {
        "cwd": "apps/frontend/seller-ui"
      },
      "dependsOn": [
        "build"
      ]
    },
    "build-deps": {
      "dependsOn": [
        "^build"
      ]
    },
    "watch-deps": {
      "continuous": true,
      "dependsOn": [
        "build-deps"
      ],
      "command": "npx nx watch --projects seller-ui --includeDependentProjects -- npx nx build-deps seller-ui"
    }
  },
  "15598186309063003081": {
    "build": {
      "command": "next build",
      "options": {
        "cwd": "apps/frontend/user-ui",
        "tty": false
      },
      "dependsOn": [
        "^build"
      ],
      "cache": true,
      "inputs": [
        "default",
        "^production",
        {
          "externalDependencies": [
            "next"
          ]
        }
      ],
      "outputs": [
        "{workspaceRoot}/apps/frontend/user-ui/.next/!(cache)/**/*",
        "{workspaceRoot}/apps/frontend/user-ui/.next/!(cache)"
      ]
    },
    "dev": {
      "continuous": true,
      "command": "next dev",
      "options": {
        "cwd": "apps/frontend/user-ui"
      }
    },
    "start": {
      "continuous": true,
      "command": "next start",
      "options": {
        "cwd": "apps/frontend/user-ui"
      },
      "dependsOn": [
        "build"
      ]
    },
    "serve-static": {
      "continuous": true,
      "command": "next start",
      "options": {
        "cwd": "apps/frontend/user-ui"
      },
      "dependsOn": [
        "build"
      ]
    },
    "build-deps": {
      "dependsOn": [
        "^build"
      ]
    },
    "watch-deps": {
      "continuous": true,
      "dependsOn": [
        "build-deps"
      ],
      "command": "npx nx watch --projects user-ui --includeDependentProjects -- npx nx build-deps user-ui"
    }
  },
  "13778349475600135293": {
    "build": {
      "command": "next build",
      "options": {
        "cwd": "apps/frontend/seller-ui",
        "tty": false
      },
      "dependsOn": [
        "^build"
      ],
      "cache": true,
      "inputs": [
        "default",
        "^production",
        {
          "externalDependencies": [
            "next"
          ]
        }
      ],
      "outputs": [
        "{workspaceRoot}/apps/frontend/seller-ui/.next/!(cache)/**/*",
        "{workspaceRoot}/apps/frontend/seller-ui/.next/!(cache)"
      ]
    },
    "dev": {
      "continuous": true,
      "command": "next dev",
      "options": {
        "cwd": "apps/frontend/seller-ui"
      }
    },
    "start": {
      "continuous": true,
      "command": "next start",
      "options": {
        "cwd": "apps/frontend/seller-ui"
      },
      "dependsOn": [
        "build"
      ]
    },
    "serve-static": {
      "continuous": true,
      "command": "next start",
      "options": {
        "cwd": "apps/frontend/seller-ui"
      },
      "dependsOn": [
        "build"
      ]
    },
    "build-deps": {
      "dependsOn": [
        "^build"
      ]
    },
    "watch-deps": {
      "continuous": true,
      "dependsOn": [
        "build-deps"
      ],
      "command": "npx nx watch --projects seller-ui --includeDependentProjects -- npx nx build-deps seller-ui"
    }
  },
  "13144493486494568310": {
    "build": {
      "command": "next build",
      "options": {
        "cwd": "apps/frontend/user-ui",
        "tty": false
      },
      "dependsOn": [
        "^build"
      ],
      "cache": true,
      "inputs": [
        "default",
        "^production",
        {
          "externalDependencies": [
            "next"
          ]
        }
      ],
      "outputs": [
        "{workspaceRoot}/apps/frontend/user-ui/.next/!(cache)/**/*",
        "{workspaceRoot}/apps/frontend/user-ui/.next/!(cache)"
      ]
    },
    "dev": {
      "continuous": true,
      "command": "next dev",
      "options": {
        "cwd": "apps/frontend/user-ui"
      }
    },
    "start": {
      "continuous": true,
      "command": "next start",
      "options": {
        "cwd": "apps/frontend/user-ui"
      },
      "dependsOn": [
        "build"
      ]
    },
    "serve-static": {
      "continuous": true,
      "command": "next start",
      "options": {
        "cwd": "apps/frontend/user-ui"
      },
      "dependsOn": [
        "build"
      ]
    },
    "build-deps": {
      "dependsOn": [
        "^build"
      ]
    },
    "watch-deps": {
      "continuous": true,
      "dependsOn": [
        "build-deps"
      ],
      "command": "npx nx watch --projects user-ui --includeDependentProjects -- npx nx build-deps user-ui"
    }
  },
  "2481308465746787566": {
    "build": {
      "command": "next build",
      "options": {
        "cwd": "apps/frontend/seller-ui",
        "tty": false
      },
      "dependsOn": [
        "^build"
      ],
      "cache": true,
      "inputs": [
        "default",
        "^production",
        {
          "externalDependencies": [
            "next"
          ]
        }
      ],
      "outputs": [
        "{workspaceRoot}/apps/frontend/seller-ui/.next/!(cache)/**/*",
        "{workspaceRoot}/apps/frontend/seller-ui/.next/!(cache)"
      ]
    },
    "dev": {
      "continuous": true,
      "command": "next dev",
      "options": {
        "cwd": "apps/frontend/seller-ui"
      }
    },
    "start": {
      "continuous": true,
      "command": "next start",
      "options": {
        "cwd": "apps/frontend/seller-ui"
      },
      "dependsOn": [
        "build"
      ]
    },
    "serve-static": {
      "continuous": true,
      "command": "next start",
      "options": {
        "cwd": "apps/frontend/seller-ui"
      },
      "dependsOn": [
        "build"
      ]
    },
    "build-deps": {
      "dependsOn": [
        "^build"
      ]
    },
    "watch-deps": {
      "continuous": true,
      "dependsOn": [
        "build-deps"
      ],
      "command": "npx nx watch --projects seller-ui --includeDependentProjects -- npx nx build-deps seller-ui"
    }
  },
  "17923643082363612622": {
    "build": {
      "command": "next build",
      "options": {
        "cwd": "apps/frontend/user-ui",
        "tty": false
      },
      "dependsOn": [
        "^build"
      ],
      "cache": true,
      "inputs": [
        "default",
        "^production",
        {
          "externalDependencies": [
            "next"
          ]
        }
      ],
      "outputs": [
        "{workspaceRoot}/apps/frontend/user-ui/.next/!(cache)/**/*",
        "{workspaceRoot}/apps/frontend/user-ui/.next/!(cache)"
      ]
    },
    "dev": {
      "continuous": true,
      "command": "next dev",
      "options": {
        "cwd": "apps/frontend/user-ui"
      }
    },
    "start": {
      "continuous": true,
      "command": "next start",
      "options": {
        "cwd": "apps/frontend/user-ui"
      },
      "dependsOn": [
        "build"
      ]
    },
    "serve-static": {
      "continuous": true,
      "command": "next start",
      "options": {
        "cwd": "apps/frontend/user-ui"
      },
      "dependsOn": [
        "build"
      ]
    },
    "build-deps": {
      "dependsOn": [
        "^build"
      ]
    },
    "watch-deps": {
      "continuous": true,
      "dependsOn": [
        "build-deps"
      ],
      "command": "npx nx watch --projects user-ui --includeDependentProjects -- npx nx build-deps user-ui"
    }
  },
  "16610609669752917814": {
    "build": {
      "command": "next build",
      "options": {
        "cwd": "apps/frontend/seller-ui",
        "tty": false
      },
      "dependsOn": [
        "^build"
      ],
      "cache": true,
      "inputs": [
        "default",
        "^production",
        {
          "externalDependencies": [
            "next"
          ]
        }
      ],
      "outputs": [
        "{workspaceRoot}/apps/frontend/seller-ui/.next/!(cache)/**/*",
        "{workspaceRoot}/apps/frontend/seller-ui/.next/!(cache)"
      ]
    },
    "dev": {
      "continuous": true,
      "command": "next dev",
      "options": {
        "cwd": "apps/frontend/seller-ui"
      }
    },
    "start": {
      "continuous": true,
      "command": "next start",
      "options": {
        "cwd": "apps/frontend/seller-ui"
      },
      "dependsOn": [
        "build"
      ]
    },
    "serve-static": {
      "continuous": true,
      "command": "next start",
      "options": {
        "cwd": "apps/frontend/seller-ui"
      },
      "dependsOn": [
        "build"
      ]
    },
    "build-deps": {
      "dependsOn": [
        "^build"
      ]
    },
    "watch-deps": {
      "continuous": true,
      "dependsOn": [
        "build-deps"
      ],
      "command": "npx nx watch --projects seller-ui --includeDependentProjects -- npx nx build-deps seller-ui"
    }
  },
  "11949648465786007128": {
    "build": {
      "command": "next build",
      "options": {
        "cwd": "apps/frontend/user-ui",
        "tty": false
      },
      "dependsOn": [
        "^build"
      ],
      "cache": true,
      "inputs": [
        "default",
        "^production",
        {
          "externalDependencies": [
            "next"
          ]
        }
      ],
      "outputs": [
        "{workspaceRoot}/apps/frontend/user-ui/.next/!(cache)/**/*",
        "{workspaceRoot}/apps/frontend/user-ui/.next/!(cache)"
      ]
    },
    "dev": {
      "continuous": true,
      "command": "next dev",
      "options": {
        "cwd": "apps/frontend/user-ui"
      }
    },
    "start": {
      "continuous": true,
      "command": "next start",
      "options": {
        "cwd": "apps/frontend/user-ui"
      },
      "dependsOn": [
        "build"
      ]
    },
    "serve-static": {
      "continuous": true,
      "command": "next start",
      "options": {
        "cwd": "apps/frontend/user-ui"
      },
      "dependsOn": [
        "build"
      ]
    },
    "build-deps": {
      "dependsOn": [
        "^build"
      ]
    },
    "watch-deps": {
      "continuous": true,
      "dependsOn": [
        "build-deps"
      ],
      "command": "npx nx watch --projects user-ui --includeDependentProjects -- npx nx build-deps user-ui"
    }
  },
  "15272678242857263135": {
    "build": {
      "command": "next build",
      "options": {
        "cwd": "apps/frontend/seller-ui",
        "tty": false
      },
      "dependsOn": [
        "^build"
      ],
      "cache": true,
      "inputs": [
        "default",
        "^production",
        {
          "externalDependencies": [
            "next"
          ]
        }
      ],
      "outputs": [
        "{workspaceRoot}/apps/frontend/seller-ui/.next/!(cache)/**/*",
        "{workspaceRoot}/apps/frontend/seller-ui/.next/!(cache)"
      ]
    },
    "dev": {
      "continuous": true,
      "command": "next dev",
      "options": {
        "cwd": "apps/frontend/seller-ui"
      }
    },
    "start": {
      "continuous": true,
      "command": "next start",
      "options": {
        "cwd": "apps/frontend/seller-ui"
      },
      "dependsOn": [
        "build"
      ]
    },
    "serve-static": {
      "continuous": true,
      "command": "next start",
      "options": {
        "cwd": "apps/frontend/seller-ui"
      },
      "dependsOn": [
        "build"
      ]
    },
    "build-deps": {
      "dependsOn": [
        "^build"
      ]
    },
    "watch-deps": {
      "continuous": true,
      "dependsOn": [
        "build-deps"
      ],
      "command": "npx nx watch --projects seller-ui --includeDependentProjects -- npx nx build-deps seller-ui"
    }
  },
  "16602801960847420275": {
    "build": {
      "command": "next build",
      "options": {
        "cwd": "apps/frontend/user-ui",
        "tty": false
      },
      "dependsOn": [
        "^build"
      ],
      "cache": true,
      "inputs": [
        "default",
        "^production",
        {
          "externalDependencies": [
            "next"
          ]
        }
      ],
      "outputs": [
        "{workspaceRoot}/apps/frontend/user-ui/.next/!(cache)/**/*",
        "{workspaceRoot}/apps/frontend/user-ui/.next/!(cache)"
      ]
    },
    "dev": {
      "continuous": true,
      "command": "next dev",
      "options": {
        "cwd": "apps/frontend/user-ui"
      }
    },
    "start": {
      "continuous": true,
      "command": "next start",
      "options": {
        "cwd": "apps/frontend/user-ui"
      },
      "dependsOn": [
        "build"
      ]
    },
    "serve-static": {
      "continuous": true,
      "command": "next start",
      "options": {
        "cwd": "apps/frontend/user-ui"
      },
      "dependsOn": [
        "build"
      ]
    },
    "build-deps": {
      "dependsOn": [
        "^build"
      ]
    },
    "watch-deps": {
      "continuous": true,
      "dependsOn": [
        "build-deps"
      ],
      "command": "npx nx watch --projects user-ui --includeDependentProjects -- npx nx build-deps user-ui"
    }
  },
  "7290232673086734022": {
    "build": {
      "command": "next build",
      "options": {
        "cwd": "apps/frontend/seller-ui",
        "tty": false
      },
      "dependsOn": [
        "^build"
      ],
      "cache": true,
      "inputs": [
        "default",
        "^production",
        {
          "externalDependencies": [
            "next"
          ]
        }
      ],
      "outputs": [
        "{workspaceRoot}/apps/frontend/seller-ui/.next/!(cache)/**/*",
        "{workspaceRoot}/apps/frontend/seller-ui/.next/!(cache)"
      ]
    },
    "dev": {
      "continuous": true,
      "command": "next dev",
      "options": {
        "cwd": "apps/frontend/seller-ui"
      }
    },
    "start": {
      "continuous": true,
      "command": "next start",
      "options": {
        "cwd": "apps/frontend/seller-ui"
      },
      "dependsOn": [
        "build"
      ]
    },
    "serve-static": {
      "continuous": true,
      "command": "next start",
      "options": {
        "cwd": "apps/frontend/seller-ui"
      },
      "dependsOn": [
        "build"
      ]
    },
    "build-deps": {
      "dependsOn": [
        "^build"
      ]
    },
    "watch-deps": {
      "continuous": true,
      "dependsOn": [
        "build-deps"
      ],
      "command": "npx nx watch --projects seller-ui --includeDependentProjects -- npx nx build-deps seller-ui"
    }
  },
  "5243615005319222579": {
    "build": {
      "command": "next build",
      "options": {
        "cwd": "apps/frontend/user-ui",
        "tty": false
      },
      "dependsOn": [
        "^build"
      ],
      "cache": true,
      "inputs": [
        "default",
        "^production",
        {
          "externalDependencies": [
            "next"
          ]
        }
      ],
      "outputs": [
        "{workspaceRoot}/apps/frontend/user-ui/.next/!(cache)/**/*",
        "{workspaceRoot}/apps/frontend/user-ui/.next/!(cache)"
      ]
    },
    "dev": {
      "continuous": true,
      "command": "next dev",
      "options": {
        "cwd": "apps/frontend/user-ui"
      }
    },
    "start": {
      "continuous": true,
      "command": "next start",
      "options": {
        "cwd": "apps/frontend/user-ui"
      },
      "dependsOn": [
        "build"
      ]
    },
    "serve-static": {
      "continuous": true,
      "command": "next start",
      "options": {
        "cwd": "apps/frontend/user-ui"
      },
      "dependsOn": [
        "build"
      ]
    },
    "build-deps": {
      "dependsOn": [
        "^build"
      ]
    },
    "watch-deps": {
      "continuous": true,
      "dependsOn": [
        "build-deps"
      ],
      "command": "npx nx watch --projects user-ui --includeDependentProjects -- npx nx build-deps user-ui"
    }
  },
  "6443984341743963171": {
    "build": {
      "command": "next build",
      "options": {
        "cwd": "apps/frontend/user-ui",
        "tty": false
      },
      "dependsOn": [
        "^build"
      ],
      "cache": true,
      "inputs": [
        "default",
        "^production",
        {
          "externalDependencies": [
            "next"
          ]
        }
      ],
      "outputs": [
        "{workspaceRoot}/apps/frontend/user-ui/.next/!(cache)/**/*",
        "{workspaceRoot}/apps/frontend/user-ui/.next/!(cache)"
      ]
    },
    "dev": {
      "continuous": true,
      "command": "next dev",
      "options": {
        "cwd": "apps/frontend/user-ui"
      }
    },
    "start": {
      "continuous": true,
      "command": "next start",
      "options": {
        "cwd": "apps/frontend/user-ui"
      },
      "dependsOn": [
        "build"
      ]
    },
    "serve-static": {
      "continuous": true,
      "command": "next start",
      "options": {
        "cwd": "apps/frontend/user-ui"
      },
      "dependsOn": [
        "build"
      ]
    },
    "build-deps": {
      "dependsOn": [
        "^build"
      ]
    },
    "watch-deps": {
      "continuous": true,
      "dependsOn": [
        "build-deps"
      ],
      "command": "npx nx watch --projects user-ui --includeDependentProjects -- npx nx build-deps user-ui"
    }
  },
  "4030442959895890648": {
    "build": {
      "command": "next build",
      "options": {
        "cwd": "apps/frontend/user-ui",
        "tty": false
      },
      "dependsOn": [
        "^build"
      ],
      "cache": true,
      "inputs": [
        "default",
        "^production",
        {
          "externalDependencies": [
            "next"
          ]
        }
      ],
      "outputs": [
        "{workspaceRoot}/apps/frontend/user-ui/.next/!(cache)/**/*",
        "{workspaceRoot}/apps/frontend/user-ui/.next/!(cache)"
      ]
    },
    "dev": {
      "continuous": true,
      "command": "next dev",
      "options": {
        "cwd": "apps/frontend/user-ui"
      }
    },
    "start": {
      "continuous": true,
      "command": "next start",
      "options": {
        "cwd": "apps/frontend/user-ui"
      },
      "dependsOn": [
        "build"
      ]
    },
    "serve-static": {
      "continuous": true,
      "command": "next start",
      "options": {
        "cwd": "apps/frontend/user-ui"
      },
      "dependsOn": [
        "build"
      ]
    },
    "build-deps": {
      "dependsOn": [
        "^build"
      ]
    },
    "watch-deps": {
      "continuous": true,
      "dependsOn": [
        "build-deps"
      ],
      "command": "npx nx watch --projects user-ui --includeDependentProjects -- npx nx build-deps user-ui"
    }
  },
  "157951567343639069": {
    "build": {
      "command": "next build",
      "options": {
        "cwd": "apps/frontend/user-ui",
        "tty": false
      },
      "dependsOn": [
        "^build"
      ],
      "cache": true,
      "inputs": [
        "default",
        "^production",
        {
          "externalDependencies": [
            "next"
          ]
        }
      ],
      "outputs": [
        "{workspaceRoot}/apps/frontend/user-ui/.next/!(cache)/**/*",
        "{workspaceRoot}/apps/frontend/user-ui/.next/!(cache)"
      ]
    },
    "dev": {
      "continuous": true,
      "command": "next dev",
      "options": {
        "cwd": "apps/frontend/user-ui"
      }
    },
    "start": {
      "continuous": true,
      "command": "next start",
      "options": {
        "cwd": "apps/frontend/user-ui"
      },
      "dependsOn": [
        "build"
      ]
    },
    "serve-static": {
      "continuous": true,
      "command": "next start",
      "options": {
        "cwd": "apps/frontend/user-ui"
      },
      "dependsOn": [
        "build"
      ]
    },
    "build-deps": {
      "dependsOn": [
        "^build"
      ]
    },
    "watch-deps": {
      "continuous": true,
      "dependsOn": [
        "build-deps"
      ],
      "command": "npx nx watch --projects user-ui --includeDependentProjects -- npx nx build-deps user-ui"
    }
  },
  "17325604392575337378": {
    "build": {
      "command": "next build",
      "options": {
        "cwd": "apps/frontend/user-ui",
        "tty": false
      },
      "dependsOn": [
        "^build"
      ],
      "cache": true,
      "inputs": [
        "default",
        "^production",
        {
          "externalDependencies": [
            "next"
          ]
        }
      ],
      "outputs": [
        "{workspaceRoot}/apps/frontend/user-ui/.next/!(cache)/**/*",
        "{workspaceRoot}/apps/frontend/user-ui/.next/!(cache)"
      ]
    },
    "dev": {
      "continuous": true,
      "command": "next dev",
      "options": {
        "cwd": "apps/frontend/user-ui"
      }
    },
    "start": {
      "continuous": true,
      "command": "next start",
      "options": {
        "cwd": "apps/frontend/user-ui"
      },
      "dependsOn": [
        "build"
      ]
    },
    "serve-static": {
      "continuous": true,
      "command": "next start",
      "options": {
        "cwd": "apps/frontend/user-ui"
      },
      "dependsOn": [
        "build"
      ]
    },
    "build-deps": {
      "dependsOn": [
        "^build"
      ]
    },
    "watch-deps": {
      "continuous": true,
      "dependsOn": [
        "build-deps"
      ],
      "command": "npx nx watch --projects user-ui --includeDependentProjects -- npx nx build-deps user-ui"
    }
  },
  "4805225212388520261": {
    "build": {
      "command": "next build",
      "options": {
        "cwd": "apps/frontend/user-ui",
        "tty": false
      },
      "dependsOn": [
        "^build"
      ],
      "cache": true,
      "inputs": [
        "default",
        "^production",
        {
          "externalDependencies": [
            "next"
          ]
        }
      ],
      "outputs": [
        "{workspaceRoot}/apps/frontend/user-ui/.next/!(cache)/**/*",
        "{workspaceRoot}/apps/frontend/user-ui/.next/!(cache)"
      ]
    },
    "dev": {
      "continuous": true,
      "command": "next dev",
      "options": {
        "cwd": "apps/frontend/user-ui"
      }
    },
    "start": {
      "continuous": true,
      "command": "next start",
      "options": {
        "cwd": "apps/frontend/user-ui"
      },
      "dependsOn": [
        "build"
      ]
    },
    "serve-static": {
      "continuous": true,
      "command": "next start",
      "options": {
        "cwd": "apps/frontend/user-ui"
      },
      "dependsOn": [
        "build"
      ]
    },
    "build-deps": {
      "dependsOn": [
        "^build"
      ]
    },
    "watch-deps": {
      "continuous": true,
      "dependsOn": [
        "build-deps"
      ],
      "command": "npx nx watch --projects user-ui --includeDependentProjects -- npx nx build-deps user-ui"
    }
  },
  "14675955763160731562": {
    "build": {
      "command": "next build",
      "options": {
        "cwd": "apps/frontend/user-ui",
        "tty": false
      },
      "dependsOn": [
        "^build"
      ],
      "cache": true,
      "inputs": [
        "default",
        "^production",
        {
          "externalDependencies": [
            "next"
          ]
        }
      ],
      "outputs": [
        "{workspaceRoot}/apps/frontend/user-ui/.next/!(cache)/**/*",
        "{workspaceRoot}/apps/frontend/user-ui/.next/!(cache)"
      ]
    },
    "dev": {
      "continuous": true,
      "command": "next dev",
      "options": {
        "cwd": "apps/frontend/user-ui"
      }
    },
    "start": {
      "continuous": true,
      "command": "next start",
      "options": {
        "cwd": "apps/frontend/user-ui"
      },
      "dependsOn": [
        "build"
      ]
    },
    "serve-static": {
      "continuous": true,
      "command": "next start",
      "options": {
        "cwd": "apps/frontend/user-ui"
      },
      "dependsOn": [
        "build"
      ]
    },
    "build-deps": {
      "dependsOn": [
        "^build"
      ]
    },
    "watch-deps": {
      "continuous": true,
      "dependsOn": [
        "build-deps"
      ],
      "command": "npx nx watch --projects user-ui --includeDependentProjects -- npx nx build-deps user-ui"
    }
  },
  "1789881248493909768": {
    "build": {
      "command": "next build",
      "options": {
        "cwd": "apps/frontend/user-ui",
        "tty": false
      },
      "dependsOn": [
        "^build"
      ],
      "cache": true,
      "inputs": [
        "default",
        "^production",
        {
          "externalDependencies": [
            "next"
          ]
        }
      ],
      "outputs": [
        "{workspaceRoot}/apps/frontend/user-ui/.next/!(cache)/**/*",
        "{workspaceRoot}/apps/frontend/user-ui/.next/!(cache)"
      ]
    },
    "dev": {
      "continuous": true,
      "command": "next dev",
      "options": {
        "cwd": "apps/frontend/user-ui"
      }
    },
    "start": {
      "continuous": true,
      "command": "next start",
      "options": {
        "cwd": "apps/frontend/user-ui"
      },
      "dependsOn": [
        "build"
      ]
    },
    "serve-static": {
      "continuous": true,
      "command": "next start",
      "options": {
        "cwd": "apps/frontend/user-ui"
      },
      "dependsOn": [
        "build"
      ]
    },
    "build-deps": {
      "dependsOn": [
        "^build"
      ]
    },
    "watch-deps": {
      "continuous": true,
      "dependsOn": [
        "build-deps"
      ],
      "command": "npx nx watch --projects user-ui --includeDependentProjects -- npx nx build-deps user-ui"
    }
  },
  "14256285029237703976": {
    "build": {
      "command": "next build",
      "options": {
        "cwd": "apps/frontend/user-ui",
        "tty": false
      },
      "dependsOn": [
        "^build"
      ],
      "cache": true,
      "inputs": [
        "default",
        "^production",
        {
          "externalDependencies": [
            "next"
          ]
        }
      ],
      "outputs": [
        "{workspaceRoot}/apps/frontend/user-ui/.next/!(cache)/**/*",
        "{workspaceRoot}/apps/frontend/user-ui/.next/!(cache)"
      ]
    },
    "dev": {
      "continuous": true,
      "command": "next dev",
      "options": {
        "cwd": "apps/frontend/user-ui"
      }
    },
    "start": {
      "continuous": true,
      "command": "next start",
      "options": {
        "cwd": "apps/frontend/user-ui"
      },
      "dependsOn": [
        "build"
      ]
    },
    "serve-static": {
      "continuous": true,
      "command": "next start",
      "options": {
        "cwd": "apps/frontend/user-ui"
      },
      "dependsOn": [
        "build"
      ]
    },
    "build-deps": {
      "dependsOn": [
        "^build"
      ]
    },
    "watch-deps": {
      "continuous": true,
      "dependsOn": [
        "build-deps"
      ],
      "command": "npx nx watch --projects user-ui --includeDependentProjects -- npx nx build-deps user-ui"
    }
  },
  "6921689281386666233": {
    "build": {
      "command": "next build",
      "options": {
        "cwd": "apps/frontend/user-ui",
        "tty": false
      },
      "dependsOn": [
        "^build"
      ],
      "cache": true,
      "inputs": [
        "default",
        "^production",
        {
          "externalDependencies": [
            "next"
          ]
        }
      ],
      "outputs": [
        "{workspaceRoot}/apps/frontend/user-ui/.next/!(cache)/**/*",
        "{workspaceRoot}/apps/frontend/user-ui/.next/!(cache)"
      ]
    },
    "dev": {
      "continuous": true,
      "command": "next dev",
      "options": {
        "cwd": "apps/frontend/user-ui"
      }
    },
    "start": {
      "continuous": true,
      "command": "next start",
      "options": {
        "cwd": "apps/frontend/user-ui"
      },
      "dependsOn": [
        "build"
      ]
    },
    "serve-static": {
      "continuous": true,
      "command": "next start",
      "options": {
        "cwd": "apps/frontend/user-ui"
      },
      "dependsOn": [
        "build"
      ]
    },
    "build-deps": {
      "dependsOn": [
        "^build"
      ]
    },
    "watch-deps": {
      "continuous": true,
      "dependsOn": [
        "build-deps"
      ],
      "command": "npx nx watch --projects user-ui --includeDependentProjects -- npx nx build-deps user-ui"
    }
  },
  "5246241376633195082": {
    "build": {
      "command": "next build",
      "options": {
        "cwd": "apps/frontend/user-ui",
        "tty": false
      },
      "dependsOn": [
        "^build"
      ],
      "cache": true,
      "inputs": [
        "default",
        "^production",
        {
          "externalDependencies": [
            "next"
          ]
        }
      ],
      "outputs": [
        "{workspaceRoot}/apps/frontend/user-ui/.next/!(cache)/**/*",
        "{workspaceRoot}/apps/frontend/user-ui/.next/!(cache)"
      ]
    },
    "dev": {
      "continuous": true,
      "command": "next dev",
      "options": {
        "cwd": "apps/frontend/user-ui"
      }
    },
    "start": {
      "continuous": true,
      "command": "next start",
      "options": {
        "cwd": "apps/frontend/user-ui"
      },
      "dependsOn": [
        "build"
      ]
    },
    "serve-static": {
      "continuous": true,
      "command": "next start",
      "options": {
        "cwd": "apps/frontend/user-ui"
      },
      "dependsOn": [
        "build"
      ]
    },
    "build-deps": {
      "dependsOn": [
        "^build"
      ]
    },
    "watch-deps": {
      "continuous": true,
      "dependsOn": [
        "build-deps"
      ],
      "command": "npx nx watch --projects user-ui --includeDependentProjects -- npx nx build-deps user-ui"
    }
  },
  "1570193176279293816": {
    "build": {
      "command": "next build",
      "options": {
        "cwd": "apps/frontend/user-ui",
        "tty": false
      },
      "dependsOn": [
        "^build"
      ],
      "cache": true,
      "inputs": [
        "default",
        "^production",
        {
          "externalDependencies": [
            "next"
          ]
        }
      ],
      "outputs": [
        "{workspaceRoot}/apps/frontend/user-ui/.next/!(cache)/**/*",
        "{workspaceRoot}/apps/frontend/user-ui/.next/!(cache)"
      ]
    },
    "dev": {
      "continuous": true,
      "command": "next dev",
      "options": {
        "cwd": "apps/frontend/user-ui"
      }
    },
    "start": {
      "continuous": true,
      "command": "next start",
      "options": {
        "cwd": "apps/frontend/user-ui"
      },
      "dependsOn": [
        "build"
      ]
    },
    "serve-static": {
      "continuous": true,
      "command": "next start",
      "options": {
        "cwd": "apps/frontend/user-ui"
      },
      "dependsOn": [
        "build"
      ]
    },
    "build-deps": {
      "dependsOn": [
        "^build"
      ]
    },
    "watch-deps": {
      "continuous": true,
      "dependsOn": [
        "build-deps"
      ],
      "command": "npx nx watch --projects user-ui --includeDependentProjects -- npx nx build-deps user-ui"
    }
  },
  "8406169348618624312": {
    "build": {
      "command": "next build",
      "options": {
        "cwd": "apps/frontend/user-ui",
        "tty": false
      },
      "dependsOn": [
        "^build"
      ],
      "cache": true,
      "inputs": [
        "default",
        "^production",
        {
          "externalDependencies": [
            "next"
          ]
        }
      ],
      "outputs": [
        "{workspaceRoot}/apps/frontend/user-ui/.next/!(cache)/**/*",
        "{workspaceRoot}/apps/frontend/user-ui/.next/!(cache)"
      ]
    },
    "dev": {
      "continuous": true,
      "command": "next dev",
      "options": {
        "cwd": "apps/frontend/user-ui"
      }
    },
    "start": {
      "continuous": true,
      "command": "next start",
      "options": {
        "cwd": "apps/frontend/user-ui"
      },
      "dependsOn": [
        "build"
      ]
    },
    "serve-static": {
      "continuous": true,
      "command": "next start",
      "options": {
        "cwd": "apps/frontend/user-ui"
      },
      "dependsOn": [
        "build"
      ]
    },
    "build-deps": {
      "dependsOn": [
        "^build"
      ]
    },
    "watch-deps": {
      "continuous": true,
      "dependsOn": [
        "build-deps"
      ],
      "command": "npx nx watch --projects user-ui --includeDependentProjects -- npx nx build-deps user-ui"
    }
  },
  "5261718850563946268": {
    "build": {
      "command": "next build",
      "options": {
        "cwd": "apps/frontend/user-ui",
        "tty": false
      },
      "dependsOn": [
        "^build"
      ],
      "cache": true,
      "inputs": [
        "default",
        "^production",
        {
          "externalDependencies": [
            "next"
          ]
        }
      ],
      "outputs": [
        "{workspaceRoot}/apps/frontend/user-ui/.next/!(cache)/**/*",
        "{workspaceRoot}/apps/frontend/user-ui/.next/!(cache)"
      ]
    },
    "dev": {
      "continuous": true,
      "command": "next dev",
      "options": {
        "cwd": "apps/frontend/user-ui"
      }
    },
    "start": {
      "continuous": true,
      "command": "next start",
      "options": {
        "cwd": "apps/frontend/user-ui"
      },
      "dependsOn": [
        "build"
      ]
    },
    "serve-static": {
      "continuous": true,
      "command": "next start",
      "options": {
        "cwd": "apps/frontend/user-ui"
      },
      "dependsOn": [
        "build"
      ]
    },
    "build-deps": {
      "dependsOn": [
        "^build"
      ]
    },
    "watch-deps": {
      "continuous": true,
      "dependsOn": [
        "build-deps"
      ],
      "command": "npx nx watch --projects user-ui --includeDependentProjects -- npx nx build-deps user-ui"
    }
  },
  "8712542131988227922": {
    "build": {
      "command": "next build",
      "options": {
        "cwd": "apps/frontend/user-ui",
        "tty": false
      },
      "dependsOn": [
        "^build"
      ],
      "cache": true,
      "inputs": [
        "default",
        "^production",
        {
          "externalDependencies": [
            "next"
          ]
        }
      ],
      "outputs": [
        "{workspaceRoot}/apps/frontend/user-ui/.next/!(cache)/**/*",
        "{workspaceRoot}/apps/frontend/user-ui/.next/!(cache)"
      ]
    },
    "dev": {
      "continuous": true,
      "command": "next dev",
      "options": {
        "cwd": "apps/frontend/user-ui"
      }
    },
    "start": {
      "continuous": true,
      "command": "next start",
      "options": {
        "cwd": "apps/frontend/user-ui"
      },
      "dependsOn": [
        "build"
      ]
    },
    "serve-static": {
      "continuous": true,
      "command": "next start",
      "options": {
        "cwd": "apps/frontend/user-ui"
      },
      "dependsOn": [
        "build"
      ]
    },
    "build-deps": {
      "dependsOn": [
        "^build"
      ]
    },
    "watch-deps": {
      "continuous": true,
      "dependsOn": [
        "build-deps"
      ],
      "command": "npx nx watch --projects user-ui --includeDependentProjects -- npx nx build-deps user-ui"
    }
  },
  "13039590252254343662": {
    "build": {
      "command": "next build",
      "options": {
        "cwd": "apps/frontend/user-ui",
        "tty": false
      },
      "dependsOn": [
        "^build"
      ],
      "cache": true,
      "inputs": [
        "default",
        "^production",
        {
          "externalDependencies": [
            "next"
          ]
        }
      ],
      "outputs": [
        "{workspaceRoot}/apps/frontend/user-ui/.next/!(cache)/**/*",
        "{workspaceRoot}/apps/frontend/user-ui/.next/!(cache)"
      ]
    },
    "dev": {
      "continuous": true,
      "command": "next dev",
      "options": {
        "cwd": "apps/frontend/user-ui"
      }
    },
    "start": {
      "continuous": true,
      "command": "next start",
      "options": {
        "cwd": "apps/frontend/user-ui"
      },
      "dependsOn": [
        "build"
      ]
    },
    "serve-static": {
      "continuous": true,
      "command": "next start",
      "options": {
        "cwd": "apps/frontend/user-ui"
      },
      "dependsOn": [
        "build"
      ]
    },
    "build-deps": {
      "dependsOn": [
        "^build"
      ]
    },
    "watch-deps": {
      "continuous": true,
      "dependsOn": [
        "build-deps"
      ],
      "command": "npx nx watch --projects user-ui --includeDependentProjects -- npx nx build-deps user-ui"
    }
  },
  "2462061781334533238": {
    "build": {
      "command": "next build",
      "options": {
        "cwd": "apps/frontend/user-ui",
        "tty": false
      },
      "dependsOn": [
        "^build"
      ],
      "cache": true,
      "inputs": [
        "default",
        "^production",
        {
          "externalDependencies": [
            "next"
          ]
        }
      ],
      "outputs": [
        "{workspaceRoot}/apps/frontend/user-ui/.next/!(cache)/**/*",
        "{workspaceRoot}/apps/frontend/user-ui/.next/!(cache)"
      ]
    },
    "dev": {
      "continuous": true,
      "command": "next dev",
      "options": {
        "cwd": "apps/frontend/user-ui"
      }
    },
    "start": {
      "continuous": true,
      "command": "next start",
      "options": {
        "cwd": "apps/frontend/user-ui"
      },
      "dependsOn": [
        "build"
      ]
    },
    "serve-static": {
      "continuous": true,
      "command": "next start",
      "options": {
        "cwd": "apps/frontend/user-ui"
      },
      "dependsOn": [
        "build"
      ]
    },
    "build-deps": {
      "dependsOn": [
        "^build"
      ]
    },
    "watch-deps": {
      "continuous": true,
      "dependsOn": [
        "build-deps"
      ],
      "command": "npx nx watch --projects user-ui --includeDependentProjects -- npx nx build-deps user-ui"
    }
  },
  "2275768016850301234": {
    "build": {
      "command": "next build",
      "options": {
        "cwd": "apps/frontend/user-ui",
        "tty": false
      },
      "dependsOn": [
        "^build"
      ],
      "cache": true,
      "inputs": [
        "default",
        "^production",
        {
          "externalDependencies": [
            "next"
          ]
        }
      ],
      "outputs": [
        "{workspaceRoot}/apps/frontend/user-ui/.next/!(cache)/**/*",
        "{workspaceRoot}/apps/frontend/user-ui/.next/!(cache)"
      ]
    },
    "dev": {
      "continuous": true,
      "command": "next dev",
      "options": {
        "cwd": "apps/frontend/user-ui"
      }
    },
    "start": {
      "continuous": true,
      "command": "next start",
      "options": {
        "cwd": "apps/frontend/user-ui"
      },
      "dependsOn": [
        "build"
      ]
    },
    "serve-static": {
      "continuous": true,
      "command": "next start",
      "options": {
        "cwd": "apps/frontend/user-ui"
      },
      "dependsOn": [
        "build"
      ]
    },
    "build-deps": {
      "dependsOn": [
        "^build"
      ]
    },
    "watch-deps": {
      "continuous": true,
      "dependsOn": [
        "build-deps"
      ],
      "command": "npx nx watch --projects user-ui --includeDependentProjects -- npx nx build-deps user-ui"
    }
  },
  "3187897191494366967": {
    "build": {
      "command": "next build",
      "options": {
        "cwd": "apps/frontend/seller-ui",
        "tty": false
      },
      "dependsOn": [
        "^build"
      ],
      "cache": true,
      "inputs": [
        "default",
        "^production",
        {
          "externalDependencies": [
            "next"
          ]
        }
      ],
      "outputs": [
        "{workspaceRoot}/apps/frontend/seller-ui/.next/!(cache)/**/*",
        "{workspaceRoot}/apps/frontend/seller-ui/.next/!(cache)"
      ]
    },
    "dev": {
      "continuous": true,
      "command": "next dev",
      "options": {
        "cwd": "apps/frontend/seller-ui"
      }
    },
    "start": {
      "continuous": true,
      "command": "next start",
      "options": {
        "cwd": "apps/frontend/seller-ui"
      },
      "dependsOn": [
        "build"
      ]
    },
    "serve-static": {
      "continuous": true,
      "command": "next start",
      "options": {
        "cwd": "apps/frontend/seller-ui"
      },
      "dependsOn": [
        "build"
      ]
    },
    "build-deps": {
      "dependsOn": [
        "^build"
      ]
    },
    "watch-deps": {
      "continuous": true,
      "dependsOn": [
        "build-deps"
      ],
      "command": "npx nx watch --projects seller-ui --includeDependentProjects -- npx nx build-deps seller-ui"
    }
  },
  "7484575037479417472": {
    "build": {
      "command": "next build",
      "options": {
        "cwd": "apps/frontend/user-ui",
        "tty": false
      },
      "dependsOn": [
        "^build"
      ],
      "cache": true,
      "inputs": [
        "default",
        "^production",
        {
          "externalDependencies": [
            "next"
          ]
        }
      ],
      "outputs": [
        "{workspaceRoot}/apps/frontend/user-ui/.next/!(cache)/**/*",
        "{workspaceRoot}/apps/frontend/user-ui/.next/!(cache)"
      ]
    },
    "dev": {
      "continuous": true,
      "command": "next dev",
      "options": {
        "cwd": "apps/frontend/user-ui"
      }
    },
    "start": {
      "continuous": true,
      "command": "next start",
      "options": {
        "cwd": "apps/frontend/user-ui"
      },
      "dependsOn": [
        "build"
      ]
    },
    "serve-static": {
      "continuous": true,
      "command": "next start",
      "options": {
        "cwd": "apps/frontend/user-ui"
      },
      "dependsOn": [
        "build"
      ]
    },
    "build-deps": {
      "dependsOn": [
        "^build"
      ]
    },
    "watch-deps": {
      "continuous": true,
      "dependsOn": [
        "build-deps"
      ],
      "command": "npx nx watch --projects user-ui --includeDependentProjects -- npx nx build-deps user-ui"
    }
  },
  "8617697843908087995": {
    "build": {
      "command": "next build",
      "options": {
        "cwd": "apps/frontend/user-ui",
        "tty": false
      },
      "dependsOn": [
        "^build"
      ],
      "cache": true,
      "inputs": [
        "default",
        "^production",
        {
          "externalDependencies": [
            "next"
          ]
        }
      ],
      "outputs": [
        "{workspaceRoot}/apps/frontend/user-ui/.next/!(cache)/**/*",
        "{workspaceRoot}/apps/frontend/user-ui/.next/!(cache)"
      ]
    },
    "dev": {
      "continuous": true,
      "command": "next dev",
      "options": {
        "cwd": "apps/frontend/user-ui"
      }
    },
    "start": {
      "continuous": true,
      "command": "next start",
      "options": {
        "cwd": "apps/frontend/user-ui"
      },
      "dependsOn": [
        "build"
      ]
    },
    "serve-static": {
      "continuous": true,
      "command": "next start",
      "options": {
        "cwd": "apps/frontend/user-ui"
      },
      "dependsOn": [
        "build"
      ]
    },
    "build-deps": {
      "dependsOn": [
        "^build"
      ]
    },
    "watch-deps": {
      "continuous": true,
      "dependsOn": [
        "build-deps"
      ],
      "command": "npx nx watch --projects user-ui --includeDependentProjects -- npx nx build-deps user-ui"
    }
  },
  "11553903557227560633": {
    "build": {
      "command": "next build",
      "options": {
        "cwd": "apps/frontend/user-ui",
        "tty": false
      },
      "dependsOn": [
        "^build"
      ],
      "cache": true,
      "inputs": [
        "default",
        "^production",
        {
          "externalDependencies": [
            "next"
          ]
        }
      ],
      "outputs": [
        "{workspaceRoot}/apps/frontend/user-ui/.next/!(cache)/**/*",
        "{workspaceRoot}/apps/frontend/user-ui/.next/!(cache)"
      ]
    },
    "dev": {
      "continuous": true,
      "command": "next dev",
      "options": {
        "cwd": "apps/frontend/user-ui"
      }
    },
    "start": {
      "continuous": true,
      "command": "next start",
      "options": {
        "cwd": "apps/frontend/user-ui"
      },
      "dependsOn": [
        "build"
      ]
    },
    "serve-static": {
      "continuous": true,
      "command": "next start",
      "options": {
        "cwd": "apps/frontend/user-ui"
      },
      "dependsOn": [
        "build"
      ]
    },
    "build-deps": {
      "dependsOn": [
        "^build"
      ]
    },
    "watch-deps": {
      "continuous": true,
      "dependsOn": [
        "build-deps"
      ],
      "command": "npx nx watch --projects user-ui --includeDependentProjects -- npx nx build-deps user-ui"
    }
  },
  "2332294259667955306": {
    "build": {
      "command": "next build",
      "options": {
        "cwd": "apps/frontend/user-ui",
        "tty": false
      },
      "dependsOn": [
        "^build"
      ],
      "cache": true,
      "inputs": [
        "default",
        "^production",
        {
          "externalDependencies": [
            "next"
          ]
        }
      ],
      "outputs": [
        "{workspaceRoot}/apps/frontend/user-ui/.next/!(cache)/**/*",
        "{workspaceRoot}/apps/frontend/user-ui/.next/!(cache)"
      ]
    },
    "dev": {
      "continuous": true,
      "command": "next dev",
      "options": {
        "cwd": "apps/frontend/user-ui"
      }
    },
    "start": {
      "continuous": true,
      "command": "next start",
      "options": {
        "cwd": "apps/frontend/user-ui"
      },
      "dependsOn": [
        "build"
      ]
    },
    "serve-static": {
      "continuous": true,
      "command": "next start",
      "options": {
        "cwd": "apps/frontend/user-ui"
      },
      "dependsOn": [
        "build"
      ]
    },
    "build-deps": {
      "dependsOn": [
        "^build"
      ]
    },
    "watch-deps": {
      "continuous": true,
      "dependsOn": [
        "build-deps"
      ],
      "command": "npx nx watch --projects user-ui --includeDependentProjects -- npx nx build-deps user-ui"
    }
  },
  "14366138443020752269": {
    "build": {
      "command": "next build",
      "options": {
        "cwd": "apps/frontend/user-ui",
        "tty": false
      },
      "dependsOn": [
        "^build"
      ],
      "cache": true,
      "inputs": [
        "default",
        "^production",
        {
          "externalDependencies": [
            "next"
          ]
        }
      ],
      "outputs": [
        "{workspaceRoot}/apps/frontend/user-ui/.next/!(cache)/**/*",
        "{workspaceRoot}/apps/frontend/user-ui/.next/!(cache)"
      ]
    },
    "dev": {
      "continuous": true,
      "command": "next dev",
      "options": {
        "cwd": "apps/frontend/user-ui"
      }
    },
    "start": {
      "continuous": true,
      "command": "next start",
      "options": {
        "cwd": "apps/frontend/user-ui"
      },
      "dependsOn": [
        "build"
      ]
    },
    "serve-static": {
      "continuous": true,
      "command": "next start",
      "options": {
        "cwd": "apps/frontend/user-ui"
      },
      "dependsOn": [
        "build"
      ]
    },
    "build-deps": {
      "dependsOn": [
        "^build"
      ]
    },
    "watch-deps": {
      "continuous": true,
      "dependsOn": [
        "build-deps"
      ],
      "command": "npx nx watch --projects user-ui --includeDependentProjects -- npx nx build-deps user-ui"
    }
  },
  "1444780325242282932": {
    "build": {
      "command": "next build",
      "options": {
        "cwd": "apps/frontend/user-ui",
        "tty": false
      },
      "dependsOn": [
        "^build"
      ],
      "cache": true,
      "inputs": [
        "default",
        "^production",
        {
          "externalDependencies": [
            "next"
          ]
        }
      ],
      "outputs": [
        "{workspaceRoot}/apps/frontend/user-ui/.next/!(cache)/**/*",
        "{workspaceRoot}/apps/frontend/user-ui/.next/!(cache)"
      ]
    },
    "dev": {
      "continuous": true,
      "command": "next dev",
      "options": {
        "cwd": "apps/frontend/user-ui"
      }
    },
    "start": {
      "continuous": true,
      "command": "next start",
      "options": {
        "cwd": "apps/frontend/user-ui"
      },
      "dependsOn": [
        "build"
      ]
    },
    "serve-static": {
      "continuous": true,
      "command": "next start",
      "options": {
        "cwd": "apps/frontend/user-ui"
      },
      "dependsOn": [
        "build"
      ]
    },
    "build-deps": {
      "dependsOn": [
        "^build"
      ]
    },
    "watch-deps": {
      "continuous": true,
      "dependsOn": [
        "build-deps"
      ],
      "command": "npx nx watch --projects user-ui --includeDependentProjects -- npx nx build-deps user-ui"
    }
  },
  "113816559327668115": {
    "build": {
      "command": "next build",
      "options": {
        "cwd": "apps/frontend/user-ui",
        "tty": false
      },
      "dependsOn": [
        "^build"
      ],
      "cache": true,
      "inputs": [
        "default",
        "^production",
        {
          "externalDependencies": [
            "next"
          ]
        }
      ],
      "outputs": [
        "{workspaceRoot}/apps/frontend/user-ui/.next/!(cache)/**/*",
        "{workspaceRoot}/apps/frontend/user-ui/.next/!(cache)"
      ]
    },
    "dev": {
      "continuous": true,
      "command": "next dev",
      "options": {
        "cwd": "apps/frontend/user-ui"
      }
    },
    "start": {
      "continuous": true,
      "command": "next start",
      "options": {
        "cwd": "apps/frontend/user-ui"
      },
      "dependsOn": [
        "build"
      ]
    },
    "serve-static": {
      "continuous": true,
      "command": "next start",
      "options": {
        "cwd": "apps/frontend/user-ui"
      },
      "dependsOn": [
        "build"
      ]
    },
    "build-deps": {
      "dependsOn": [
        "^build"
      ]
    },
    "watch-deps": {
      "continuous": true,
      "dependsOn": [
        "build-deps"
      ],
      "command": "npx nx watch --projects user-ui --includeDependentProjects -- npx nx build-deps user-ui"
    }
  },
  "14793494869095660828": {
    "build": {
      "command": "next build",
      "options": {
        "cwd": "apps/frontend/user-ui",
        "tty": false
      },
      "dependsOn": [
        "^build"
      ],
      "cache": true,
      "inputs": [
        "default",
        "^production",
        {
          "externalDependencies": [
            "next"
          ]
        }
      ],
      "outputs": [
        "{workspaceRoot}/apps/frontend/user-ui/.next/!(cache)/**/*",
        "{workspaceRoot}/apps/frontend/user-ui/.next/!(cache)"
      ]
    },
    "dev": {
      "continuous": true,
      "command": "next dev",
      "options": {
        "cwd": "apps/frontend/user-ui"
      }
    },
    "start": {
      "continuous": true,
      "command": "next start",
      "options": {
        "cwd": "apps/frontend/user-ui"
      },
      "dependsOn": [
        "build"
      ]
    },
    "serve-static": {
      "continuous": true,
      "command": "next start",
      "options": {
        "cwd": "apps/frontend/user-ui"
      },
      "dependsOn": [
        "build"
      ]
    },
    "build-deps": {
      "dependsOn": [
        "^build"
      ]
    },
    "watch-deps": {
      "continuous": true,
      "dependsOn": [
        "build-deps"
      ],
      "command": "npx nx watch --projects user-ui --includeDependentProjects -- npx nx build-deps user-ui"
    }
  },
  "17167851099942229199": {
    "build": {
      "command": "next build",
      "options": {
        "cwd": "apps/frontend/user-ui",
        "tty": false
      },
      "dependsOn": [
        "^build"
      ],
      "cache": true,
      "inputs": [
        "default",
        "^production",
        {
          "externalDependencies": [
            "next"
          ]
        }
      ],
      "outputs": [
        "{workspaceRoot}/apps/frontend/user-ui/.next/!(cache)/**/*",
        "{workspaceRoot}/apps/frontend/user-ui/.next/!(cache)"
      ]
    },
    "dev": {
      "continuous": true,
      "command": "next dev",
      "options": {
        "cwd": "apps/frontend/user-ui"
      }
    },
    "start": {
      "continuous": true,
      "command": "next start",
      "options": {
        "cwd": "apps/frontend/user-ui"
      },
      "dependsOn": [
        "build"
      ]
    },
    "serve-static": {
      "continuous": true,
      "command": "next start",
      "options": {
        "cwd": "apps/frontend/user-ui"
      },
      "dependsOn": [
        "build"
      ]
    },
    "build-deps": {
      "dependsOn": [
        "^build"
      ]
    },
    "watch-deps": {
      "continuous": true,
      "dependsOn": [
        "build-deps"
      ],
      "command": "npx nx watch --projects user-ui --includeDependentProjects -- npx nx build-deps user-ui"
    }
  },
  "12693676402518843981": {
    "build": {
      "command": "next build",
      "options": {
        "cwd": "apps/frontend/user-ui",
        "tty": false
      },
      "dependsOn": [
        "^build"
      ],
      "cache": true,
      "inputs": [
        "default",
        "^production",
        {
          "externalDependencies": [
            "next"
          ]
        }
      ],
      "outputs": [
        "{workspaceRoot}/apps/frontend/user-ui/.next/!(cache)/**/*",
        "{workspaceRoot}/apps/frontend/user-ui/.next/!(cache)"
      ]
    },
    "dev": {
      "continuous": true,
      "command": "next dev",
      "options": {
        "cwd": "apps/frontend/user-ui"
      }
    },
    "start": {
      "continuous": true,
      "command": "next start",
      "options": {
        "cwd": "apps/frontend/user-ui"
      },
      "dependsOn": [
        "build"
      ]
    },
    "serve-static": {
      "continuous": true,
      "command": "next start",
      "options": {
        "cwd": "apps/frontend/user-ui"
      },
      "dependsOn": [
        "build"
      ]
    },
    "build-deps": {
      "dependsOn": [
        "^build"
      ]
    },
    "watch-deps": {
      "continuous": true,
      "dependsOn": [
        "build-deps"
      ],
      "command": "npx nx watch --projects user-ui --includeDependentProjects -- npx nx build-deps user-ui"
    }
  },
  "14991365034027652563": {
    "build": {
      "command": "next build",
      "options": {
        "cwd": "apps/frontend/user-ui",
        "tty": false
      },
      "dependsOn": [
        "^build"
      ],
      "cache": true,
      "inputs": [
        "default",
        "^production",
        {
          "externalDependencies": [
            "next"
          ]
        }
      ],
      "outputs": [
        "{workspaceRoot}/apps/frontend/user-ui/.next/!(cache)/**/*",
        "{workspaceRoot}/apps/frontend/user-ui/.next/!(cache)"
      ]
    },
    "dev": {
      "continuous": true,
      "command": "next dev",
      "options": {
        "cwd": "apps/frontend/user-ui"
      }
    },
    "start": {
      "continuous": true,
      "command": "next start",
      "options": {
        "cwd": "apps/frontend/user-ui"
      },
      "dependsOn": [
        "build"
      ]
    },
    "serve-static": {
      "continuous": true,
      "command": "next start",
      "options": {
        "cwd": "apps/frontend/user-ui"
      },
      "dependsOn": [
        "build"
      ]
    },
    "build-deps": {
      "dependsOn": [
        "^build"
      ]
    },
    "watch-deps": {
      "continuous": true,
      "dependsOn": [
        "build-deps"
      ],
      "command": "npx nx watch --projects user-ui --includeDependentProjects -- npx nx build-deps user-ui"
    }
  },
  "18329803329364689402": {
    "build": {
      "command": "next build",
      "options": {
        "cwd": "apps/frontend/user-ui",
        "tty": false
      },
      "dependsOn": [
        "^build"
      ],
      "cache": true,
      "inputs": [
        "default",
        "^production",
        {
          "externalDependencies": [
            "next"
          ]
        }
      ],
      "outputs": [
        "{workspaceRoot}/apps/frontend/user-ui/.next/!(cache)/**/*",
        "{workspaceRoot}/apps/frontend/user-ui/.next/!(cache)"
      ]
    },
    "dev": {
      "continuous": true,
      "command": "next dev",
      "options": {
        "cwd": "apps/frontend/user-ui"
      }
    },
    "start": {
      "continuous": true,
      "command": "next start",
      "options": {
        "cwd": "apps/frontend/user-ui"
      },
      "dependsOn": [
        "build"
      ]
    },
    "serve-static": {
      "continuous": true,
      "command": "next start",
      "options": {
        "cwd": "apps/frontend/user-ui"
      },
      "dependsOn": [
        "build"
      ]
    },
    "build-deps": {
      "dependsOn": [
        "^build"
      ]
    },
    "watch-deps": {
      "continuous": true,
      "dependsOn": [
        "build-deps"
      ],
      "command": "npx nx watch --projects user-ui --includeDependentProjects -- npx nx build-deps user-ui"
    }
  },
  "9986361089439410393": {
    "build": {
      "command": "next build",
      "options": {
        "cwd": "apps/frontend/user-ui",
        "tty": false
      },
      "dependsOn": [
        "^build"
      ],
      "cache": true,
      "inputs": [
        "default",
        "^production",
        {
          "externalDependencies": [
            "next"
          ]
        }
      ],
      "outputs": [
        "{workspaceRoot}/apps/frontend/user-ui/.next/!(cache)/**/*",
        "{workspaceRoot}/apps/frontend/user-ui/.next/!(cache)"
      ]
    },
    "dev": {
      "continuous": true,
      "command": "next dev",
      "options": {
        "cwd": "apps/frontend/user-ui"
      }
    },
    "start": {
      "continuous": true,
      "command": "next start",
      "options": {
        "cwd": "apps/frontend/user-ui"
      },
      "dependsOn": [
        "build"
      ]
    },
    "serve-static": {
      "continuous": true,
      "command": "next start",
      "options": {
        "cwd": "apps/frontend/user-ui"
      },
      "dependsOn": [
        "build"
      ]
    },
    "build-deps": {
      "dependsOn": [
        "^build"
      ]
    },
    "watch-deps": {
      "continuous": true,
      "dependsOn": [
        "build-deps"
      ],
      "command": "npx nx watch --projects user-ui --includeDependentProjects -- npx nx build-deps user-ui"
    }
  },
  "18188775347050878414": {
    "build": {
      "command": "next build",
      "options": {
        "cwd": "apps/frontend/user-ui",
        "tty": false
      },
      "dependsOn": [
        "^build"
      ],
      "cache": true,
      "inputs": [
        "default",
        "^production",
        {
          "externalDependencies": [
            "next"
          ]
        }
      ],
      "outputs": [
        "{workspaceRoot}/apps/frontend/user-ui/.next/!(cache)/**/*",
        "{workspaceRoot}/apps/frontend/user-ui/.next/!(cache)"
      ]
    },
    "dev": {
      "continuous": true,
      "command": "next dev",
      "options": {
        "cwd": "apps/frontend/user-ui"
      }
    },
    "start": {
      "continuous": true,
      "command": "next start",
      "options": {
        "cwd": "apps/frontend/user-ui"
      },
      "dependsOn": [
        "build"
      ]
    },
    "serve-static": {
      "continuous": true,
      "command": "next start",
      "options": {
        "cwd": "apps/frontend/user-ui"
      },
      "dependsOn": [
        "build"
      ]
    },
    "build-deps": {
      "dependsOn": [
        "^build"
      ]
    },
    "watch-deps": {
      "continuous": true,
      "dependsOn": [
        "build-deps"
      ],
      "command": "npx nx watch --projects user-ui --includeDependentProjects -- npx nx build-deps user-ui"
    }
  },
  "3930354593613618512": {
    "build": {
      "command": "next build",
      "options": {
        "cwd": "apps/frontend/user-ui",
        "tty": false
      },
      "dependsOn": [
        "^build"
      ],
      "cache": true,
      "inputs": [
        "default",
        "^production",
        {
          "externalDependencies": [
            "next"
          ]
        }
      ],
      "outputs": [
        "{workspaceRoot}/apps/frontend/user-ui/.next/!(cache)/**/*",
        "{workspaceRoot}/apps/frontend/user-ui/.next/!(cache)"
      ]
    },
    "dev": {
      "continuous": true,
      "command": "next dev",
      "options": {
        "cwd": "apps/frontend/user-ui"
      }
    },
    "start": {
      "continuous": true,
      "command": "next start",
      "options": {
        "cwd": "apps/frontend/user-ui"
      },
      "dependsOn": [
        "build"
      ]
    },
    "serve-static": {
      "continuous": true,
      "command": "next start",
      "options": {
        "cwd": "apps/frontend/user-ui"
      },
      "dependsOn": [
        "build"
      ]
    },
    "build-deps": {
      "dependsOn": [
        "^build"
      ]
    },
    "watch-deps": {
      "continuous": true,
      "dependsOn": [
        "build-deps"
      ],
      "command": "npx nx watch --projects user-ui --includeDependentProjects -- npx nx build-deps user-ui"
    }
  },
  "16432056945118929940": {
    "build": {
      "command": "next build",
      "options": {
        "cwd": "apps/frontend/user-ui",
        "tty": false
      },
      "dependsOn": [
        "^build"
      ],
      "cache": true,
      "inputs": [
        "default",
        "^production",
        {
          "externalDependencies": [
            "next"
          ]
        }
      ],
      "outputs": [
        "{workspaceRoot}/apps/frontend/user-ui/.next/!(cache)/**/*",
        "{workspaceRoot}/apps/frontend/user-ui/.next/!(cache)"
      ]
    },
    "dev": {
      "continuous": true,
      "command": "next dev",
      "options": {
        "cwd": "apps/frontend/user-ui"
      }
    },
    "start": {
      "continuous": true,
      "command": "next start",
      "options": {
        "cwd": "apps/frontend/user-ui"
      },
      "dependsOn": [
        "build"
      ]
    },
    "serve-static": {
      "continuous": true,
      "command": "next start",
      "options": {
        "cwd": "apps/frontend/user-ui"
      },
      "dependsOn": [
        "build"
      ]
    },
    "build-deps": {
      "dependsOn": [
        "^build"
      ]
    },
    "watch-deps": {
      "continuous": true,
      "dependsOn": [
        "build-deps"
      ],
      "command": "npx nx watch --projects user-ui --includeDependentProjects -- npx nx build-deps user-ui"
    }
  },
  "9634501951483093470": {
    "build": {
      "command": "next build",
      "options": {
        "cwd": "apps/frontend/user-ui",
        "tty": false
      },
      "dependsOn": [
        "^build"
      ],
      "cache": true,
      "inputs": [
        "default",
        "^production",
        {
          "externalDependencies": [
            "next"
          ]
        }
      ],
      "outputs": [
        "{workspaceRoot}/apps/frontend/user-ui/.next/!(cache)/**/*",
        "{workspaceRoot}/apps/frontend/user-ui/.next/!(cache)"
      ]
    },
    "dev": {
      "continuous": true,
      "command": "next dev",
      "options": {
        "cwd": "apps/frontend/user-ui"
      }
    },
    "start": {
      "continuous": true,
      "command": "next start",
      "options": {
        "cwd": "apps/frontend/user-ui"
      },
      "dependsOn": [
        "build"
      ]
    },
    "serve-static": {
      "continuous": true,
      "command": "next start",
      "options": {
        "cwd": "apps/frontend/user-ui"
      },
      "dependsOn": [
        "build"
      ]
    },
    "build-deps": {
      "dependsOn": [
        "^build"
      ]
    },
    "watch-deps": {
      "continuous": true,
      "dependsOn": [
        "build-deps"
      ],
      "command": "npx nx watch --projects user-ui --includeDependentProjects -- npx nx build-deps user-ui"
    }
  }
}